class_utils/__init__.py
class_utils/class_utils.py
class_utils-0.0.5.dist-info/LICENSE
class_utils-0.0.5.dist-info/METADATA
class_utils-0.0.5.dist-info/WHEEL
class_utils-0.0.5.dist-info/top_level.txt
class_utils-0.0.5.dist-info/RECORD
