Metadata-Version: 2.1
Name: class-utils
Version: 0.0.5
Summary: Utils for simplifying work with classes
Home-page: https://github.com/fly1ngDream/class-utils
Author: fly1ngDream
Author-email: fly1ngDream@protonmail.com
License: UNKNOWN
Platform: UNKNOWN
Classifier: Programming Language :: Python :: 3
Classifier: License :: OSI Approved :: MIT License
Classifier: Operating System :: OS Independent
